{"assets/images/feature_graphic.jpg":["assets/images/feature_graphic.jpg"],"assets/images/feature_graphic.jpg~":["assets/images/feature_graphic.jpg~"],"assets/images/feature_graphic.kra":["assets/images/feature_graphic.kra"],"assets/images/feature_graphic.kra~":["assets/images/feature_graphic.kra~"],"assets/images/flutter_logo.png":["assets/images/flutter_logo.png","assets/images/3.0x/flutter_logo.png","assets/images/2.0x/flutter_logo.png"],"assets/images/icon.png":["assets/images/icon.png"],"assets/images/icon.svg":["assets/images/icon.svg"]}